wolfsoftware/profiles_config/__init__.py
wolfsoftware/profiles_config/parser.py
wolfsoftware.profiles_config-0.1.1.dist-info/LICENSE.md
wolfsoftware.profiles_config-0.1.1.dist-info/METADATA
wolfsoftware.profiles_config-0.1.1.dist-info/WHEEL
wolfsoftware.profiles_config-0.1.1.dist-info/top_level.txt
wolfsoftware.profiles_config-0.1.1.dist-info/RECORD
