Metadata-Version: 2.1
Name: wolfsoftware.profiles-config
Version: 0.1.1
Summary: A basic package for managing profile based configuration files.
Home-page: https://github.com/DevelopersToolbox/profiles-config-package
Author: Wolf Software
Author-email: pypi@wolfsoftware.com
License: MIT
Project-URL: Source, https://github.com/DevelopersToolbox/profiles-config-package
Project-URL: Tracker, https://github.com/wDevelopersToolbox/profiles-config-package/issues/
Project-URL: Documentation, https://github.com/DevelopersToolbox/profiles-config-package
Project-URL: Sponsor, https://github.com/sponsors/WolfSoftware
Keywords: python,profiles,configuration
Classifier: Development Status :: 4 - Beta
Classifier: Environment :: Console
Classifier: Intended Audience :: Developers
Classifier: License :: OSI Approved :: MIT License
Classifier: Programming Language :: Python :: 3
Classifier: Programming Language :: Python :: 3.9
Classifier: Programming Language :: Python :: 3.10
Classifier: Programming Language :: Python :: 3.11
Classifier: Programming Language :: Python :: 3.12
Classifier: Operating System :: OS Independent
Classifier: Topic :: Software Development
Requires-Python: >=3.9
License-File: LICENSE.md
